{"type":"object","properties":{"body":{"description":"Request body","type":"object","properties":{"BranchID":{"type":["null","number"]},"VendorName":{"type":"string"},"AccountingVendorID":{"type":["null","string"]},"BillingTerms":{"type":["null","string"]},"Active":{"type":"boolean"}},"additionalProperties":false,"required":["VendorName"],"advanced":[]},"api_version":{"description":"Original parameter name: api-version","type":"string"}},"additionalProperties":false,"required":["body"],"$schema":"http://json-schema.org/draft-07/schema#","advanced":[]}